wechat_ocr/__init__.py
wechat_ocr/default_callback.py
wechat_ocr/mmmojo_dll.py
wechat_ocr/ocr_manager.py
wechat_ocr/ocr_protobuf_pb2.py
wechat_ocr/utility_protobuf_pb2.py
wechat_ocr/winapi.py
wechat_ocr/xplugin_manager.py
wechat_ocr-0.0.2.dist-info/METADATA
wechat_ocr-0.0.2.dist-info/WHEEL
wechat_ocr-0.0.2.dist-info/licenses/LICENSE
wechat_ocr-0.0.2.dist-info/RECORD
