Metadata-Version: 2.1
Name: wechat-ocr
Version: 0.0.2
Summary: wechat ocr
Project-URL: Homepage, https://github.com/kanadeblisst00/wechat_ocr
Project-URL: Bug Tracker, https://github.com/kanadeblisst00/wechat_ocr/issues
Author-email: kanadeblisst <kanade@blisst.cn>
License: Copyright (c) 2018 The Python Packaging Authority
License-File: LICENSE
Classifier: License :: OSI Approved :: MIT License
Classifier: Operating System :: Microsoft :: Windows
Classifier: Programming Language :: Python :: 3
Requires-Python: >=3.7
Requires-Dist: protobuf==3.20.3
